miRBaseMiner/__init__.py
miRBaseMiner-0.2.dist-info/DESCRIPTION.rst
miRBaseMiner-0.2.dist-info/METADATA
miRBaseMiner-0.2.dist-info/RECORD
miRBaseMiner-0.2.dist-info/WHEEL
miRBaseMiner-0.2.dist-info/metadata.json
miRBaseMiner-0.2.dist-info/top_level.txt
miRBaseMiner-0.2.dist-info/zip-safe
