Metadata-Version: 2.0
Name: miRBaseMiner
Version: 0.2
Summary: Mining the miRNA annotation in miRBase for comprehensive understanding in miRNA annotation reference before implementing in miRNA study.
Home-page: https://github.com/joey0214/miRBaseMiner
Author: Xiangfu (Joey) Zhong
Author-email: joey.zhong.cn@gmail.com
License: GNU GPLv3
Keywords: miRBase microRNA miRNA
Platform: UNKNOWN
Classifier: Development Status :: 4 - Beta
Classifier: License :: OSI Approved :: GNU General Public License v3 (GPLv3)
Classifier: Programming Language :: Python :: 2.7
Requires-Python: >=2.6, !=3.0.*, !=3.1.*, !=3.2.*, <4
Requires-Dist: biopython
Requires-Dist: editdistance
